ChemMod/ChemMod.py
ChemMod/__init__.py
ChemMod/__main__.py
ChemMod/equation/M.py
ChemMod/equation/__init__.py
ChemMod/equation/element_data.py
ChemMod/equation/equil.py
ChemMod/info/__init__.py
ChemMod/plot/__init__.py
ChemMod/plot/arrhenius_plot.py
ChemMod/plot/bjerrum_plot.py
ChemMod/plot/element_data.py
ChemMod/plot/gibbs_plot.py
ChemMod/plot/order_plot.py
Chem.Mod-0.0.2.dist-info/COPYING.txt
Chem.Mod-0.0.2.dist-info/LICENSE.txt
Chem.Mod-0.0.2.dist-info/METADATA
Chem.Mod-0.0.2.dist-info/WHEEL
Chem.Mod-0.0.2.dist-info/top_level.txt
Chem.Mod-0.0.2.dist-info/RECORD
