Metadata-Version: 2.1
Name: Chem.Mod
Version: 0.0.2
Summary: Python program for practical plotting and calculation in chemistry. Chem.Mod is developed as a userfriendly python package for chemistry students. The package contains a variety of different useful plot functions and formula functions from chemistry e.g. buffer diagrams, gibs energy functions, reaction kinetics order plot linear regression.
Author-email: August Jacobi <augustjacobi5@gmail.com>
Project-URL: Homepage, https://www.youtube.com/watch?v=dQw4w9WgXcQ
Classifier: Programming Language :: Python :: 3
Classifier: License :: OSI Approved :: GNU General Public License v3 or later (GPLv3+)
Classifier: Operating System :: OS Independent
Requires-Python: >=3.9
License-File: LICENSE.txt
License-File: COPYING.txt
